LICENSE
README.md
setup.cfg
setup.py
yopta/__init__.py
yopta/slova.py
yopta/yopta.py
yopta.egg-info/PKG-INFO
yopta.egg-info/SOURCES.txt
yopta.egg-info/dependency_links.txt
yopta.egg-info/not-zip-safe
yopta.egg-info/top_level.txt