Metadata-Version: 2.1
Name: yopta
Version: 2022.1.23
Summary: Перевод методов, атрибутов и функций на пацанский для python!
Home-page: https://github.com/aqur1n/yopta.py
Author: aqur1n
License: UNKNOWN
Platform: UNKNOWN
License-File: LICENSE
